{
  "name": "Pacote",
  "entryPoints": [
    "./packages/array",
    "./packages/bloom-filter",
    "./packages/bloom-search",
    "./packages/computus",
    "./packages/emitter",
    "./packages/error",
    "./packages/ffetch",
    "./packages/flux-actions",
    "./packages/get-style",
    "./packages/iff",
    "./packages/immutable",
    "./packages/interpolate",
    "./packages/is-plain-object",
    "./packages/jest-either",
    "./packages/linked-list",
    "./packages/lru-cache",
    "./packages/memoize",
    "./packages/non-empty-array",
    "./packages/option",
    "./packages/pipe",
    "./packages/pixels",
    "./packages/react-use-outside",
    "./packages/react-with-props",
    "./packages/result",
    "./packages/retry",
    "./packages/shuffle",
    "./packages/throttle",
    "./packages/u32",
    "./packages/u64",
    "./packages/validation",
    "./packages/xxhash"
  ],
  "entryPointStrategy": "packages",
  "out": "./docs",
  "navigationLinks": {},
  "sidebarLinks": {},
  "excludePrivate": true,
  "excludeExternals": true,
  "githubPages": true,
  "pretty": true,
  "skipErrorChecking": true
}
